Metadata-Version: 1.1
Name: tjpybot
Version: 0.3
Summary: A playful way to learn coding with Python and TJBot
Home-page: https://github.com/sprintingkiwi/tjpybot
Author: ASPHI Onlus
Author-email: sprintingkiwi@gmail.com
License: UNKNOWN
Download-URL: https://github.com/sprintingkiwi/tjpybot/tarball/0.1
Keywords: learning,education,TJBot,robotics
Platform: UNKNOWN
